algo/__init__.py
algo/automl/__init__.py
algo/automl/automl.py
algo/automl/utils.py
algo/features/__init__.py
algo/features/preprocessor.py
algo/ml/__init__.py
algo/ml/base.py
algo/ml/classification.py
algo/ml/regression.py
algo/task/__init__.py
algo/task/task.py
algo_auto_ml-0.1.7.dist-info/LICENSE
algo_auto_ml-0.1.7.dist-info/METADATA
algo_auto_ml-0.1.7.dist-info/WHEEL
algo_auto_ml-0.1.7.dist-info/top_level.txt
algo_auto_ml-0.1.7.dist-info/RECORD
