Metadata-Version: 2.1
Name: algo-auto-ml
Version: 0.1.7
Summary: AutoML library for binary classification and regression tasks
Home-page: https://github.com/lllchak/algo
Author: Pavel Lyulchak
Author-email: mediumchak@yandex.ru
License: MIT
Platform: UNKNOWN
Classifier: Development Status :: 1 - Planning
Classifier: Intended Audience :: Science/Research
Classifier: Programming Language :: Python
License-File: LICENSE
Requires-Dist: lightgbm
Requires-Dist: numpy
Requires-Dist: pandas
Requires-Dist: scikit-learn
Requires-Dist: xgboost
